msg2po/__init__.py
msg2po/bgforge_config.py
msg2po/common.py
msg2po/config.py
msg2po/core.py
msg2po/diff_male_female_po_to_csv.py
msg2po/dir2msgstr.py
msg2po/female_csv2po.py
msg2po/file2msgstr.py
msg2po/file2po.py
msg2po/lowercase.py
msg2po/msgmerge.py
msg2po/po2file.py
msg2po/poify.py
msg2po/resave_po.py
msg2po/unfuzzy.py
msg2po/unfuzzy.yml
msg2po/unfuzzy_cassidy.py
msg2po/unpoify.py
msg2po-1.4.3.dist-info/METADATA
msg2po-1.4.3.dist-info/WHEEL
msg2po-1.4.3.dist-info/entry_points.txt
msg2po-1.4.3.dist-info/RECORD
